compiletojsonschema/__init__.py
compiletojsonschema/compiletojsonschema.py
compiletojsonschema/cli/__init__.py
compiletojsonschema/cli/__main__.py
tests/__init__.py
tests/test_codelist.py
tests/test_error.py
tests/test_set_additional_properties_false_everywhere.py
tests/test_simple.py
compiletojsonschema-0.5.0.dist-info/METADATA
compiletojsonschema-0.5.0.dist-info/WHEEL
compiletojsonschema-0.5.0.dist-info/entry_points.txt
compiletojsonschema-0.5.0.dist-info/top_level.txt
compiletojsonschema-0.5.0.dist-info/RECORD
